remove_empty_comment/__main__.py
remove_empty_comment-1.0.2.dist-info/LICENSE
remove_empty_comment-1.0.2.dist-info/METADATA
remove_empty_comment-1.0.2.dist-info/WHEEL
remove_empty_comment-1.0.2.dist-info/entry_points.txt
remove_empty_comment-1.0.2.dist-info/top_level.txt
remove_empty_comment-1.0.2.dist-info/zip-safe
remove_empty_comment-1.0.2.dist-info/RECORD
