Metadata-Version: 2.1
Name: remove-empty-comment
Version: 1.0.2
Summary: UNKNOWN
Home-page: https://github.com/Pierre-Sassoulas/remove-empty-comment/
Author: Pierre Sassoulas
Author-email: pierre.sassoulas@gmail.com
License: UNKNOWN
Platform: UNKNOWN
